LICENSE
MANIFEST.in
README.rst
setup.py
django_tts.egg-info/PKG-INFO
django_tts.egg-info/SOURCES.txt
django_tts.egg-info/dependency_links.txt
django_tts.egg-info/requires.txt
django_tts.egg-info/top_level.txt
tts/__init__.py
tts/admin.py
tts/apps.py
tts/models.py
tts/required.settings.py
tts/serializers.py
tts/tests.py
tts/urls.py
tts/views.py
tts/management/__init__.py
tts/management/commands/__init__.py
tts/management/commands/clean_sound.py
tts/migrations/0001_initial.py
tts/migrations/__init__.py
tts/tests/__init__.py
tts/tests/test_views.py