Metadata-Version: 1.1
Name: django-tts
Version: 0.2
Summary: A simple Django app to generate speach from text
Home-page: https://github.com/g10k/django-speach-synthesizer
Author: Sergey Vlasov
Author-email: g10k.info@gmail.com
License: BSD License
Platform: UNKNOWN
Classifier: Environment :: Web Environment
Classifier: Framework :: Django
Classifier: Framework :: Django :: 1.9
Classifier: Intended Audience :: Developers
Classifier: License :: OSI Approved :: BSD License
Classifier: Operating System :: OS Independent
Classifier: Programming Language :: Python
Classifier: Programming Language :: Python :: 3.5
Classifier: Topic :: Internet :: WWW/HTTP
Classifier: Topic :: Internet :: WWW/HTTP :: Dynamic Content
